ytm_fetcher/__init__.py
ytm_fetcher/api/__init__.py
ytm_fetcher/api/setup.py
ytm_fetcher/models/__init__.py
ytm_fetcher/models/playlist.py
ytm_fetcher/models/song.py
ytm_fetcher/utils/__init__.py
ytm_fetcher/utils/data.py
ytm_fetcher/utils/download.py
ytm_fetcher/utils/formatting.py
ytm_fetcher/utils/playback.py
ytm_fetcher/utils/playlist.py
ytm_fetcher/utils/song.py
ytm_fetcher-0.1.2.dist-info/METADATA
ytm_fetcher-0.1.2.dist-info/WHEEL
ytm_fetcher-0.1.2.dist-info/top_level.txt
ytm_fetcher-0.1.2.dist-info/RECORD
