Metadata-Version: 2.4
Name: ytm_fetcher
Version: 0.1.2
Summary: Small wrapper package to interface with YouTube Music
Author-email: Stefan Mueller <s.mueller0311@gmail.com>
License-Expression: MIT
Requires-Dist: ytmusicapi>=1.10.0
Requires-Dist: yt_dlp>=2025.1.15
Requires-Dist: playsound>=1.3.0
